cliEngine/__init__.py
cliEngine/cliEngine.py
cliEngine/coordinates.py
cliengine-0.0.7.1.dist-info/LICENSE
cliengine-0.0.7.1.dist-info/METADATA
cliengine-0.0.7.1.dist-info/WHEEL
cliengine-0.0.7.1.dist-info/top_level.txt
cliengine-0.0.7.1.dist-info/RECORD
